gdriveexplorer/__init__.py
gdriveexplorer/gdriveexplorer.py
gdriveexplorer-0.45.dist-info/METADATA
gdriveexplorer-0.45.dist-info/WHEEL
gdriveexplorer-0.45.dist-info/top_level.txt
gdriveexplorer-0.45.dist-info/RECORD
