Metadata-Version: 2.4
Name: gdriveexplorer
Version: 0.45
Summary: Class to help managing google drive files
Home-page: https://github.com/sunep12/gdriveexplorer
Download-URL: https://github.com/sunep12/gdriveexplorer/archive/refs/tags/v_045.tar.gz
Author: Sunep
Author-email: soporte.gdriveexplorer@gmail.com
License: GPLv3+
Requires-Dist: PyDrive2
Requires-Dist: google.colab
Requires-Dist: oauth2client
Requires-Dist: google-api-python-client
Requires-Dist: pandas
Requires-Dist: dill
Requires-Dist: polars
Requires-Dist: httplib2
Dynamic: author
Dynamic: author-email
Dynamic: download-url
Dynamic: home-page
Dynamic: license
Dynamic: requires-dist
Dynamic: summary
